[
  {
    "full_name": "internetarchive/openlibrary",
    "stargazers_count": 3051,
    "open_issues_count": 682,
    "forks_count": 736
  },
  {
    "full_name": "internetarchive/openlibrary",
    "stargazers_count": 3051,
    "open_issues_count": 682,
    "forks_count": 736
  },
  {
    "full_name": "internetarchive/iaux",
    "stargazers_count": 52,
    "open_issues_count": 104,
    "forks_count": 84
  },
  {
    "full_name": "github/india",
    "stargazers_count": 499,
    "open_issues_count": 0,
    "forks_count": 17
  }
]